[{"__type__":"cc.SpriteFrame","content":{"name":"m_enemy1","texture":"f4OZKFQ31MX6eSUbY57OFl","rect":[6,1,82,96],"offset":[0,0],"originalSize":[94,98],"capInsets":[0,0,0,0]}},{"__type__":"cc.AnimationClip","_name":"enemyGlitter","_duration":1.0166666666666666,"wrapMode":"2","curveData":{"comps":{"cc.Sprite":{"spriteFrame":[{"frame":0,"value":{"__uuid__":"0bbVUcKvlBw5/8p95TudNO"}},{"frame":0.5,"value":{"__uuid__":"d8giwEADJA2qmZmJKXiINi"}},{"frame":1,"value":{"__uuid__":"d8giwEADJA2qmZmJKXiINi"}}]}}}},{"__type__":"cc.SpriteFrame","content":{"name":"m_enemy2","texture":"78KYi/h7JLw4K9USXma1Jw","rect":[6,1,82,96],"offset":[0,0],"originalSize":[94,98],"capInsets":[0,0,0,0]}}]